{
  "mcpServers": {
    "context-mcp": {
      "type": "stdio",
      "command": "cargo",
      "args": [
        "run",
        "--quiet",
        "--release",
        "-p",
        "context-mcp"
      ]
    },
    "ticket-mcp": {
      "type": "stdio",
      "command": "cargo",
      "args": [
        "run",
        "--quiet",
        "--release",
        "-p",
        "ticket-mcp"
      ]
    },
    "spec-mcp": {
      "type": "stdio",
      "command": "cargo",
      "args": [
        "run",
        "--quiet",
        "--release",
        "-p",
        "spec-mcp"
      ]
    },
    "test-mcp": {
      "type": "stdio",
      "command": "cargo",
      "args": [
        "run",
        "--quiet",
        "--release",
        "-p",
        "test-mcp"
      ]
    },
    "feedback-mcp": {
      "type": "stdio",
      "command": "cargo",
      "args": [
        "run",
        "--quiet",
        "--release",
        "-p",
        "feedback-mcp"
      ]
    },
    "session-mcp": {
      "type": "stdio",
      "command": "cargo",
      "args": ["run", "--quiet", "--release", "-p", "session-mcp"]
    },
    "peek-mcp": {
      "type": "stdio",
      "command": "cargo",
      "args": ["run", "--quiet", "--release", "-p", "peek-mcp"]
    },
    "rule-mcp": {
      "type": "stdio",
      "command": "cargo",
      "args": ["run", "--quiet", "--release", "-p", "rule-mcp"]
    },
    "audit-mcp": {
      "type": "stdio",
      "command": "cargo",
      "args": ["run", "--quiet", "--release", "-p", "audit-mcp"]
    },
    "compact-terminal-mcp": {
      "type": "stdio",
      "command": "cargo",
      "args": ["run", "--quiet", "--release", "-p", "compact-terminal-mcp"]
    },
    "log-viewer-mcp": {
      "type": "stdio",
      "command": "cargo",
      "args": [
        "run",
        "--quiet",
        "--release",
        "-p",
        "log-viewer",
        "--",
        "--mcp"
      ]
    }
  }
}
